ebi/__init__.py
ebi/appversion.py
ebi/core.py
ebi/commands/__init__.py
ebi/commands/bgdeploy.py
ebi/commands/clonedeploy.py
ebi/commands/create.py
ebi/commands/deploy.py
ebi-0.12.0.dist-info/LICENSE
ebi-0.12.0.dist-info/METADATA
ebi-0.12.0.dist-info/WHEEL
ebi-0.12.0.dist-info/entry_points.txt
ebi-0.12.0.dist-info/top_level.txt
ebi-0.12.0.dist-info/RECORD
