Metadata-Version: 2.1
Name: ebi
Version: 0.12.0
Summary: Simple CLI tool for ElasticBeanstalk with Docker
Home-page: https://github.com/hirokiky/ebi
Author: Hiroki KIYOHARA
Author-email: hirokiky@gmail.com
License: MIT
Platform: UNKNOWN
License-File: LICENSE
Requires-Dist: awsebcli (<4,>=3.7.3)
Requires-Dist: boto3 (<2,>=1.2.6)
